hash_forge/__init__.py
hash_forge/exceptions.py
hash_forge/py.typed
hash_forge/types.py
hash_forge/config/__init__.py
hash_forge/config/config_loader.py
hash_forge/config/constants.py
hash_forge/config/logging.py
hash_forge/config/settings.py
hash_forge/core/__init__.py
hash_forge/core/async_manager.py
hash_forge/core/base_hasher.py
hash_forge/core/builder.py
hash_forge/core/factory.py
hash_forge/core/manager.py
hash_forge/core/protocols.py
hash_forge/hashers/__init__.py
hash_forge/hashers/argon2_hasher.py
hash_forge/hashers/bcrypt_hasher.py
hash_forge/hashers/blake2_hasher.py
hash_forge/hashers/blake3_hasher.py
hash_forge/hashers/pbkdf2_hasher.py
hash_forge/hashers/ripemd160_hasher.py
hash_forge/hashers/scrypt_hasher.py
hash_forge/hashers/whirlpool_hasher.py
hash_forge/utils/__init__.py
hash_forge/utils/helpers.py
hash_forge-3.0.1.dist-info/METADATA
hash_forge-3.0.1.dist-info/WHEEL
hash_forge-3.0.1.dist-info/licenses/LICENSE
hash_forge-3.0.1.dist-info/RECORD
