Metadata-Version: 2.4
Name: hash-forge
Version: 3.0.1
Summary: Hash Forge is a lightweight Python library designed to simplify the process of hashing and verifying data using a variety of secure hashing algorithms.
Project-URL: Homepage, https://github.com/Zozi96/hash-forge
Project-URL: Repository, https://github.com/Zozi96/hash-forge
Project-URL: Issue Tracker, https://github.com/Zozi96/hash-forge/issues
Author-email: Zozi <zozi.fer96@gmail.com>
License-Expression: MIT
License-File: LICENSE
Keywords: RIPEMD-160,Whirlpool,argon2,bcrypt,blake2,blake3,hash,pbkdf2,scrypt,security
Classifier: Development Status :: 4 - Beta
Classifier: License :: OSI Approved :: MIT License
Classifier: Operating System :: OS Independent
Classifier: Programming Language :: Python :: 3
Classifier: Programming Language :: Python :: 3.10
Classifier: Programming Language :: Python :: 3.11
Classifier: Programming Language :: Python :: 3.12
Classifier: Programming Language :: Python :: 3.13
Requires-Python: >=3.10
Provides-Extra: argon2
Requires-Dist: argon2-cffi==25.1.0; extra == 'argon2'
Provides-Extra: bcrypt
Requires-Dist: bcrypt==5.0.0; extra == 'bcrypt'
Provides-Extra: blake3
Requires-Dist: blake3==1.0.7; extra == 'blake3'
Provides-Extra: crypto
Requires-Dist: pycryptodome==3.23.0; extra == 'crypto'
